{
  "gitSyncId": "67094ba3cb4eb2140bfd1b82_b084be64-01a7-4b18-94eb-c7d6c81cf3ef",
  "id": "podsumowanie_i18n.setup",
  "pluginId": "js-plugin",
  "pluginType": "JS",
  "unpublishedAction": {
    "actionConfiguration": {
      "encodeParamsToggle": true,
      "jsArguments": [
        {
          "name": "lang",
          "value": "polski"
        }
      ],
      "paginationType": "NONE",
      "timeoutInMillisecond": 10000
    },
    "collectionId": "podsumowanie_i18n",
    "confirmBeforeExecute": false,
    "datasource": {
      "isAutoGenerated": false,
      "name": "UNUSED_DATASOURCE",
      "pluginId": "js-plugin"
    },
    "dynamicBindingPathList": [
      {
        "key": "body"
      }
    ],
    "executeOnLoad": true,
    "fullyQualifiedName": "i18n.setup",
    "name": "setup",
    "pageId": "podsumowanie",
    "userSetOnLoad": true
  }
}