{
  "gitSyncId": "66f263e90ea81e705fc1052a_516244be-b07a-4db3-ae76-4ac9cd284c12",
  "id": "Screeny_inventory_zle_pdf_chyba.myFun2",
  "pluginId": "js-plugin",
  "pluginType": "JS",
  "unpublishedAction": {
    "actionConfiguration": {
      "encodeParamsToggle": true,
      "jsArguments": [],
      "paginationType": "NONE",
      "timeoutInMillisecond": 10000
    },
    "clientSideExecution": true,
    "collectionId": "Screeny_inventory_zle_pdf_chyba",
    "confirmBeforeExecute": false,
    "datasource": {
      "isAutoGenerated": false,
      "name": "UNUSED_DATASOURCE",
      "pluginId": "js-plugin"
    },
    "dynamicBindingPathList": [
      {
        "key": "body"
      }
    ],
    "executeOnLoad": false,
    "fullyQualifiedName": "zle_pdf_chyba.myFun2",
    "name": "myFun2",
    "pageId": "Screeny_inventory",
    "userSetOnLoad": false
  }
}